[{"action_type":"ADD_FACET","case_sensitive":"false","confidence":"0.7","enabled":"true","explanation":"Generic artifact reference marker; many false positives -> REVIEW.","facet_key":"artifact_matters","facet_value":"true","match_scope":"oracle_text","match_type":"REGEX","pattern":"\\bartifact(s)?\\b","priority":"50","rule_id":"RS_ARTIFACT_WORDING_FACET","unknown_if_ambiguous":"true"},{"action_type":"ADD_FACET","case_sensitive":"false","confidence":"0.7","enabled":"true","explanation":"Generic enchantment reference marker; REVIEW for false positives.","facet_key":"enchantment_matters","facet_value":"true","match_scope":"oracle_text","match_type":"REGEX","pattern":"\\benchantment(s)?\\b","priority":"55","rule_id":"RS_ENCHANT_WORDING_FACET","unknown_if_ambiguous":"true"},{"action_type":"ADD_TAG","case_sensitive":"false","confidence":"0.65","enabled":"true","explanation":"Primitive: artifact matters (ensure exists).","match_scope":"oracle_text","match_type":"REGEX","pattern":"\\bartifact(s)?\\b","primitive_id":"ARTIFACT_MATTERS","priority":"60","rule_id":"RS_ARTIFACT_MATTERS_TAG","unknown_if_ambiguous":"true"},{"action_type":"ADD_TAG","case_sensitive":"false","confidence":"0.65","enabled":"true","explanation":"Primitive: enchantment matters (ensure exists).","match_scope":"oracle_text","match_type":"REGEX","pattern":"\\benchantment(s)?\\b","primitive_id":"ENCHANTMENT_MATTERS","priority":"61","rule_id":"RS_ENCHANT_MATTERS_TAG","unknown_if_ambiguous":"true"},{"action_type":"ADD_FACET","case_sensitive":"false","confidence":"0.4","enabled":"true","explanation":"Colon indicates activated abilities; broad. Tighten later.","facet_key":"activated_ability","facet_value":"true","match_scope":"oracle_text","match_type":"REGEX","notes":"Mark REVIEW/unknown to avoid over-tagging.","pattern":":","priority":"100","rule_id":"RS_ACTIVATED_ABILITY_COLON_FACET","unknown_if_ambiguous":"true"},{"action_type":"ADD_FACET","case_sensitive":"false","confidence":"0.8","enabled":"true","explanation":"Tap symbol suggests tap ability as cost.","facet_key":"tap_ability","facet_value":"true","match_scope":"oracle_text","match_type":"CONTAINS","pattern":"{T}","priority":"110","rule_id":"RS_TAP_ABILITY_FACET","unknown_if_ambiguous":"true"},{"action_type":"ADD_FACET","case_sensitive":"false","confidence":"0.8","enabled":"true","explanation":"Untap wording detected.","facet_key":"untap_effect","facet_value":"true","match_scope":"oracle_text","match_type":"REGEX","pattern":"\\buntap\\b","priority":"120","rule_id":"RS_UNTAP_EFFECT_FACET","unknown_if_ambiguous":"true"},{"action_type":"ADD_FACET","case_sensitive":"false","confidence":"0.85","enabled":"true","explanation":"Untaps itself.","facet_key":"untap_scope","facet_value":"SELF","match_scope":"oracle_text","match_type":"REGEX","pattern":"untap (this|~)","priority":"121","rule_id":"RS_UNTAP_SCOPE_SELF","unknown_if_ambiguous":"true"},{"action_type":"ADD_FACET","case_sensitive":"false","confidence":"0.9","enabled":"true","explanation":"Untaps target permanent.","facet_key":"untap_scope","facet_value":"PERMANENT","match_scope":"oracle_text","match_type":"REGEX","pattern":"untap target permanent","priority":"122","rule_id":"RS_UNTAP_SCOPE_PERMANENT","unknown_if_ambiguous":"false"},{"action_type":"ADD_TAG","case_sensitive":"false","confidence":"0.75","enabled":"true","explanation":"Primitive: untap effect (ensure exists).","match_scope":"oracle_text","match_type":"REGEX","pattern":"\\buntap\\b","primitive_id":"UNTAP_EFFECT","priority":"123","rule_id":"RS_UNTAP_TAG","unknown_if_ambiguous":"true"},{"action_type":"ADD_FACET","case_sensitive":"false","confidence":"0.95","enabled":"true","explanation":"Affinity keyword.","facet_key":"affinity_like","facet_value":"true","match_scope":"oracle_text","match_type":"CONTAINS","pattern":"Affinity","priority":"150","rule_id":"RS_AFFINITY_KEYWORD","unknown_if_ambiguous":"false"},{"action_type":"ADD_TAG","case_sensitive":"false","confidence":"0.85","enabled":"true","explanation":"Primitive: affinity (ensure exists).","match_scope":"oracle_text","match_type":"CONTAINS","pattern":"Affinity","primitive_id":"AFFINITY","priority":"151","rule_id":"RS_AFFINITY_TAG","unknown_if_ambiguous":"true"},{"action_type":"ADD_FACET","case_sensitive":"false","confidence":"0.95","enabled":"true","explanation":"Improvise keyword.","facet_key":"improvise","facet_value":"true","match_scope":"oracle_text","match_type":"CONTAINS","pattern":"Improvise","priority":"160","rule_id":"RS_IMPROVISE_KEYWORD","unknown_if_ambiguous":"false"},{"action_type":"ADD_TAG","case_sensitive":"false","confidence":"0.85","enabled":"true","explanation":"Primitive: improvise (ensure exists).","match_scope":"oracle_text","match_type":"CONTAINS","pattern":"Improvise","primitive_id":"IMPROVISE","priority":"161","rule_id":"RS_IMPROVISE_TAG","unknown_if_ambiguous":"true"},{"action_type":"ADD_FACET","case_sensitive":"false","confidence":"0.95","enabled":"true","explanation":"Artifact spells cost less.","facet_key":"artifact_cost_reduction","facet_value":"true","match_scope":"oracle_text","match_type":"REGEX","pattern":"artifact spells you cast cost \\\\d+ less to cast","priority":"180","rule_id":"RS_ARTIFACT_SPELLS_COST_LESS","unknown_if_ambiguous":"false"},{"action_type":"ADD_TAG","case_sensitive":"false","confidence":"0.85","enabled":"true","explanation":"Primitive: artifact cost reduction (ensure exists).","match_scope":"oracle_text","match_type":"REGEX","pattern":"artifact spells you cast cost \\\\d+ less to cast","primitive_id":"COST_REDUCTION_ARTIFACT","priority":"181","rule_id":"RS_ARTIFACT_COST_REDUCTION_TAG","unknown_if_ambiguous":"true"},{"action_type":"ADD_FACET","case_sensitive":"false","confidence":"0.85","enabled":"true","explanation":"Equipment/equip reference.","facet_key":"equipment_related","facet_value":"true","match_scope":"oracle_text","match_type":"REGEX","pattern":"\\bequip\\b|\\bEquipment\\b","priority":"210","rule_id":"RS_EQUIP_WORDING_FACET","unknown_if_ambiguous":"true"},{"action_type":"ADD_TAG","case_sensitive":"false","confidence":"0.75","enabled":"true","explanation":"Primitive: equipment synergy (ensure exists).","match_scope":"oracle_text","match_type":"REGEX","pattern":"\\bequip\\b|\\bEquipment\\b","primitive_id":"EQUIPMENT_SYNERGY","priority":"211","rule_id":"RS_EQUIPMENT_TAG","unknown_if_ambiguous":"true"},{"action_type":"ADD_FACET","case_sensitive":"false","confidence":"0.65","enabled":"true","explanation":"Aura/enchant reference; REVIEW for false positives.","facet_key":"aura_related","facet_value":"true","match_scope":"oracle_text","match_type":"REGEX","pattern":"\\bAura\\b|\\benchant\\b","priority":"220","rule_id":"RS_AURA_WORDING_FACET","unknown_if_ambiguous":"true"},{"action_type":"ADD_TAG","case_sensitive":"false","confidence":"0.65","enabled":"true","explanation":"Primitive: aura synergy (ensure exists).","match_scope":"oracle_text","match_type":"REGEX","pattern":"\\bAura\\b|\\benchant\\b","primitive_id":"AURA_SYNERGY","priority":"221","rule_id":"RS_AURA_TAG","unknown_if_ambiguous":"true"},{"action_type":"ADD_FACET","case_sensitive":"false","confidence":"0.8","enabled":"true","explanation":"Saga/lore/chapter reference.","facet_key":"saga_related","facet_value":"true","match_scope":"oracle_text","match_type":"REGEX","pattern":"\\bSaga\\b|\\blore counter\\b|\\bchapter\\b","priority":"230","rule_id":"RS_SAGA_WORDING_FACET","unknown_if_ambiguous":"true"},{"action_type":"ADD_TAG","case_sensitive":"false","confidence":"0.7","enabled":"true","explanation":"Primitive: saga synergy (ensure exists).","match_scope":"oracle_text","match_type":"REGEX","pattern":"\\bSaga\\b|\\blore counter\\b|\\bchapter\\b","primitive_id":"SAGA_SYNERGY","priority":"231","rule_id":"RS_SAGA_TAG","unknown_if_ambiguous":"true"},{"action_type":"ADD_FACET","case_sensitive":"false","confidence":"0.95","enabled":"true","explanation":"Constellation trigger template.","facet_key":"constellation_trigger","facet_value":"true","match_scope":"oracle_text","match_type":"REGEX","pattern":"\\b(when|whenever)\\b an enchantment enters the battlefield under your control","priority":"240","rule_id":"RS_CONSTELLATION_TRIGGER_FACET","unknown_if_ambiguous":"false"},{"action_type":"ADD_TAG","case_sensitive":"false","confidence":"0.8","enabled":"true","explanation":"Primitive: constellation trigger (ensure exists).","match_scope":"oracle_text","match_type":"REGEX","pattern":"\\b(when|whenever)\\b an enchantment enters the battlefield under your control","primitive_id":"CONSTELLATION_TRIGGER","priority":"241","rule_id":"RS_CONSTELLATION_TAG","unknown_if_ambiguous":"true"},{"action_type":"ADD_FACET","case_sensitive":"false","confidence":"0.75","enabled":"true","explanation":"Tap-add mana pattern; confirm artifact type in DB.","facet_key":"mana_rock","facet_value":"true","match_scope":"oracle_text","match_type":"REGEX","notes":"Validate against card_type.","pattern":"\\{T\\}: add","priority":"280","rule_id":"RS_MANA_ROCK_FACET","unknown_if_ambiguous":"true"},{"action_type":"ADD_TAG","case_sensitive":"false","confidence":"0.7","enabled":"true","explanation":"Primitive: mana rock (ensure exists).","match_scope":"oracle_text","match_type":"REGEX","pattern":"\\{T\\}: add","primitive_id":"MANA_ROCK","priority":"281","rule_id":"RS_MANA_ROCK_TAG","unknown_if_ambiguous":"true"},{"action_type":"ADD_FACET","case_sensitive":"false","confidence":"0.95","enabled":"true","explanation":"Sacrifice artifact as activation cost.","facet_key":"artifact_sac_outlet","facet_value":"true","match_scope":"oracle_text","match_type":"REGEX","pattern":"Sacrifice an artifact:","priority":"320","rule_id":"RS_SAC_ARTIFACT_COLON","unknown_if_ambiguous":"false"},{"action_type":"ADD_FACET","case_sensitive":"false","confidence":"0.95","enabled":"true","explanation":"Sacrifice mode = COST (artifact).","facet_key":"sacrifice_mode","facet_value":"COST","match_scope":"oracle_text","match_type":"REGEX","pattern":"Sacrifice an artifact:","priority":"321","rule_id":"RS_SAC_ARTIFACT_MODE_COST","unknown_if_ambiguous":"false"},{"action_type":"ADD_TAG","case_sensitive":"false","confidence":"0.85","enabled":"true","explanation":"Primitive: artifact sac outlet (ensure exists).","match_scope":"oracle_text","match_type":"REGEX","pattern":"Sacrifice an artifact:","primitive_id":"SAC_OUTLET_ARTIFACT","priority":"322","rule_id":"RS_SAC_ARTIFACT_TAG","unknown_if_ambiguous":"true"},{"action_type":"ADD_FACET","case_sensitive":"false","confidence":"0.95","enabled":"true","explanation":"Sacrifice enchantment as activation cost.","facet_key":"enchant_sac_outlet","facet_value":"true","match_scope":"oracle_text","match_type":"REGEX","pattern":"Sacrifice an enchantment:","priority":"330","rule_id":"RS_SAC_ENCHANT_COLON","unknown_if_ambiguous":"false"},{"action_type":"ADD_TAG","case_sensitive":"false","confidence":"0.85","enabled":"true","explanation":"Primitive: enchantment sac outlet (ensure exists).","match_scope":"oracle_text","match_type":"REGEX","pattern":"Sacrifice an enchantment:","primitive_id":"SAC_OUTLET_ENCHANTMENT","priority":"331","rule_id":"RS_SAC_ENCHANT_TAG","unknown_if_ambiguous":"true"},{"action_type":"ADD_FACET","case_sensitive":"false","confidence":"0.9","enabled":"true","explanation":"Artifact recursion to battlefield.","facet_key":"artifact_recursion","facet_value":"true","match_scope":"oracle_text","match_type":"REGEX","pattern":"return target artifact card from (your|a) graveyard to the battlefield","priority":"360","rule_id":"RS_RECUR_ARTIFACT_TO_BF","unknown_if_ambiguous":"true"},{"action_type":"ADD_FACET","case_sensitive":"false","confidence":"0.95","enabled":"true","explanation":"Recursion scope artifact.","facet_key":"recursion_scope","facet_value":"ARTIFACT","match_scope":"oracle_text","match_type":"REGEX","pattern":"return target artifact card from (your|a) graveyard to the battlefield","priority":"361","rule_id":"RS_RECUR_ARTIFACT_SCOPE","unknown_if_ambiguous":"true"},{"action_type":"ADD_TAG","case_sensitive":"false","confidence":"0.85","enabled":"true","explanation":"Primitive: artifact recursion (ensure exists).","match_scope":"oracle_text","match_type":"REGEX","pattern":"return target artifact card from (your|a) graveyard to the battlefield","primitive_id":"ARTIFACT_RECURSION","priority":"362","rule_id":"RS_RECUR_ARTIFACT_TAG","unknown_if_ambiguous":"true"},{"action_type":"ADD_FACET","case_sensitive":"false","confidence":"0.9","enabled":"true","explanation":"Enchantment recursion to battlefield.","facet_key":"enchantment_recursion","facet_value":"true","match_scope":"oracle_text","match_type":"REGEX","pattern":"return target enchantment card from (your|a) graveyard to the battlefield","priority":"370","rule_id":"RS_RECUR_ENCHANT_TO_BF","unknown_if_ambiguous":"true"},{"action_type":"ADD_FACET","case_sensitive":"false","confidence":"0.95","enabled":"true","explanation":"Recursion scope enchantment.","facet_key":"recursion_scope","facet_value":"ENCHANTMENT","match_scope":"oracle_text","match_type":"REGEX","pattern":"return target enchantment card from (your|a) graveyard to the battlefield","priority":"371","rule_id":"RS_RECUR_ENCHANT_SCOPE","unknown_if_ambiguous":"true"},{"action_type":"ADD_TAG","case_sensitive":"false","confidence":"0.85","enabled":"true","explanation":"Primitive: enchantment recursion (ensure exists).","match_scope":"oracle_text","match_type":"REGEX","pattern":"return target enchantment card from (your|a) graveyard to the battlefield","primitive_id":"ENCHANTMENT_RECURSION","priority":"372","rule_id":"RS_RECUR_ENCHANT_TAG","unknown_if_ambiguous":"true"}]